[
  {
    "DATE": "",
    "NUMBER": "5",
    "CATEGORY": "기숙사",
    "WRITER": "효민생활관",
    "TITLE": "2025학년도 1학기 효민생활관/행복기숙사 관생 통합모집 안내",
    "ID": 1,
    "CONTENT": "https://www.deu.ac.kr?mode=view&articleNo=53861&article.offset=0&articleLimit=10",
    "INFO_SQUARE_ID": 193
  },
  {
    "DATE": "",
    "NUMBER": "4",
    "CATEGORY": "기숙사",
    "WRITER": "효민생활관",
    "TITLE": "2023-1학기 효민생활관/행복기숙사 관생 통합모집 공고",
    "ID": 2,
    "CONTENT": "https://www.deu.ac.kr?mode=view&articleNo=53859&article.offset=0&articleLimit=10",
    "INFO_SQUARE_ID": 194
  },
  {
    "DATE": "",
    "NUMBER": "3",
    "CATEGORY": "기숙사",
    "WRITER": "효민생활관",
    "TITLE": "[모집] 효민생활관 지도교사(부사감) 모집",
    "ID": 3,
    "CONTENT": "https://www.deu.ac.kr?mode=view&articleNo=53857&article.offset=0&articleLimit=10",
    "INFO_SQUARE_ID": 195
  },
  {
    "DATE": "",
    "NUMBER": "2",
    "CATEGORY": "기숙사",
    "WRITER": "효민생활관",
    "TITLE": "2022-2학기 효민생활관/행복기숙사 관생 모집",
    "ID": 4,
    "CONTENT": "https://www.deu.ac.kr?mode=view&articleNo=53860&article.offset=0&articleLimit=10",
    "INFO_SQUARE_ID": 196
  },
  {
    "DATE": "",
    "NUMBER": "1",
    "CATEGORY": "기숙사",
    "WRITER": "효민생활관",
    "TITLE": "2022-1학기 효민생활관 / 행복기숙사 관생 모집",
    "ID": 5,
    "CONTENT": "https://www.deu.ac.kr?mode=view&articleNo=53858&article.offset=0&articleLimit=10",
    "INFO_SQUARE_ID": 197
  },
  {
    "DATE": "",
    "NUMBER": "5",
    "CATEGORY": "기숙사",
    "WRITER": "효민생활관",
    "TITLE": "2025학년도 1학기 효민생활관/행복기숙사 관생 통합모집 안내",
    "ID": 6,
    "CONTENT": "https://www.deu.ac.kr?mode=view&articleNo=53861&article.offset=0&articleLimit=10",
    "INFO_SQUARE_ID": 198
  },
  {
    "DATE": "",
    "NUMBER": "4",
    "CATEGORY": "기숙사",
    "WRITER": "효민생활관",
    "TITLE": "2023-1학기 효민생활관/행복기숙사 관생 통합모집 공고",
    "ID": 7,
    "CONTENT": "https://www.deu.ac.kr?mode=view&articleNo=53859&article.offset=0&articleLimit=10",
    "INFO_SQUARE_ID": 199
  },
  {
    "DATE": "",
    "NUMBER": "3",
    "CATEGORY": "기숙사",
    "WRITER": "효민생활관",
    "TITLE": "[모집] 효민생활관 지도교사(부사감) 모집",
    "ID": 8,
    "CONTENT": "https://www.deu.ac.kr?mode=view&articleNo=53857&article.offset=0&articleLimit=10",
    "INFO_SQUARE_ID": 200
  },
  {
    "DATE": "",
    "NUMBER": "2",
    "CATEGORY": "기숙사",
    "WRITER": "효민생활관",
    "TITLE": "2022-2학기 효민생활관/행복기숙사 관생 모집",
    "ID": 9,
    "CONTENT": "https://www.deu.ac.kr?mode=view&articleNo=53860&article.offset=0&articleLimit=10",
    "INFO_SQUARE_ID": 201
  },
  {
    "DATE": "",
    "NUMBER": "1",
    "CATEGORY": "기숙사",
    "WRITER": "효민생활관",
    "TITLE": "2022-1학기 효민생활관 / 행복기숙사 관생 모집",
    "ID": 10,
    "CONTENT": "https://www.deu.ac.kr?mode=view&articleNo=53858&article.offset=0&articleLimit=10",
    "INFO_SQUARE_ID": 202
  },
  {
    "DATE": "",
    "NUMBER": "5",
    "CATEGORY": "기숙사",
    "WRITER": "효민생활관",
    "TITLE": "2025학년도 1학기 효민생활관/행복기숙사 관생 통합모집 안내",
    "ID": 11,
    "CONTENT": "https://www.deu.ac.kr?mode=view&articleNo=53861&article.offset=0&articleLimit=10",
    "INFO_SQUARE_ID": 203
  },
  {
    "DATE": "",
    "NUMBER": "4",
    "CATEGORY": "기숙사",
    "WRITER": "효민생활관",
    "TITLE": "2023-1학기 효민생활관/행복기숙사 관생 통합모집 공고",
    "ID": 12,
    "CONTENT": "https://www.deu.ac.kr?mode=view&articleNo=53859&article.offset=0&articleLimit=10",
    "INFO_SQUARE_ID": 204
  },
  {
    "DATE": "",
    "NUMBER": "3",
    "CATEGORY": "기숙사",
    "WRITER": "효민생활관",
    "TITLE": "[모집] 효민생활관 지도교사(부사감) 모집",
    "ID": 13,
    "CONTENT": "https://www.deu.ac.kr?mode=view&articleNo=53857&article.offset=0&articleLimit=10",
    "INFO_SQUARE_ID": 205
  },
  {
    "DATE": "",
    "NUMBER": "2",
    "CATEGORY": "기숙사",
    "WRITER": "효민생활관",
    "TITLE": "2022-2학기 효민생활관/행복기숙사 관생 모집",
    "ID": 14,
    "CONTENT": "https://www.deu.ac.kr?mode=view&articleNo=53860&article.offset=0&articleLimit=10",
    "INFO_SQUARE_ID": 206
  },
  {
    "DATE": "",
    "NUMBER": "1",
    "CATEGORY": "기숙사",
    "WRITER": "효민생활관",
    "TITLE": "2022-1학기 효민생활관 / 행복기숙사 관생 모집",
    "ID": 15,
    "CONTENT": "https://www.deu.ac.kr?mode=view&articleNo=53858&article.offset=0&articleLimit=10",
    "INFO_SQUARE_ID": 207
  },
  {
    "DATE": "",
    "NUMBER": "5",
    "CATEGORY": "기숙사",
    "WRITER": "효민생활관",
    "TITLE": "2025학년도 1학기 효민생활관/행복기숙사 관생 통합모집 안내",
    "ID": 16,
    "CONTENT": "https://www.deu.ac.kr?mode=view&articleNo=53861&article.offset=0&articleLimit=10",
    "INFO_SQUARE_ID": 208
  },
  {
    "DATE": "",
    "NUMBER": "4",
    "CATEGORY": "기숙사",
    "WRITER": "효민생활관",
    "TITLE": "2023-1학기 효민생활관/행복기숙사 관생 통합모집 공고",
    "ID": 17,
    "CONTENT": "https://www.deu.ac.kr?mode=view&articleNo=53859&article.offset=0&articleLimit=10",
    "INFO_SQUARE_ID": 209
  },
  {
    "DATE": "",
    "NUMBER": "3",
    "CATEGORY": "기숙사",
    "WRITER": "효민생활관",
    "TITLE": "[모집] 효민생활관 지도교사(부사감) 모집",
    "ID": 18,
    "CONTENT": "https://www.deu.ac.kr?mode=view&articleNo=53857&article.offset=0&articleLimit=10",
    "INFO_SQUARE_ID": 210
  },
  {
    "DATE": "",
    "NUMBER": "2",
    "CATEGORY": "기숙사",
    "WRITER": "효민생활관",
    "TITLE": "2022-2학기 효민생활관/행복기숙사 관생 모집",
    "ID": 19,
    "CONTENT": "https://www.deu.ac.kr?mode=view&articleNo=53860&article.offset=0&articleLimit=10",
    "INFO_SQUARE_ID": 211
  },
  {
    "DATE": "",
    "NUMBER": "1",
    "CATEGORY": "기숙사",
    "WRITER": "효민생활관",
    "TITLE": "2022-1학기 효민생활관 / 행복기숙사 관생 모집",
    "ID": 20,
    "CONTENT": "https://www.deu.ac.kr?mode=view&articleNo=53858&article.offset=0&articleLimit=10",
    "INFO_SQUARE_ID": 212
  },
  {
    "DATE": "",
    "NUMBER": "5",
    "CATEGORY": "기숙사",
    "WRITER": "효민생활관",
    "TITLE": "2025학년도 1학기 효민생활관/행복기숙사 관생 통합모집 안내",
    "ID": 21,
    "CONTENT": "https://www.deu.ac.kr?mode=view&articleNo=53861&article.offset=0&articleLimit=10",
    "INFO_SQUARE_ID": 213
  },
  {
    "DATE": "",
    "NUMBER": "4",
    "CATEGORY": "기숙사",
    "WRITER": "효민생활관",
    "TITLE": "2023-1학기 효민생활관/행복기숙사 관생 통합모집 공고",
    "ID": 22,
    "CONTENT": "https://www.deu.ac.kr?mode=view&articleNo=53859&article.offset=0&articleLimit=10",
    "INFO_SQUARE_ID": 214
  },
  {
    "DATE": "",
    "NUMBER": "3",
    "CATEGORY": "기숙사",
    "WRITER": "효민생활관",
    "TITLE": "[모집] 효민생활관 지도교사(부사감) 모집",
    "ID": 23,
    "CONTENT": "https://www.deu.ac.kr?mode=view&articleNo=53857&article.offset=0&articleLimit=10",
    "INFO_SQUARE_ID": 215
  },
  {
    "DATE": "",
    "NUMBER": "2",
    "CATEGORY": "기숙사",
    "WRITER": "효민생활관",
    "TITLE": "2022-2학기 효민생활관/행복기숙사 관생 모집",
    "ID": 24,
    "CONTENT": "https://www.deu.ac.kr?mode=view&articleNo=53860&article.offset=0&articleLimit=10",
    "INFO_SQUARE_ID": 216
  },
  {
    "DATE": "",
    "NUMBER": "1",
    "CATEGORY": "기숙사",
    "WRITER": "효민생활관",
    "TITLE": "2022-1학기 효민생활관 / 행복기숙사 관생 모집",
    "ID": 25,
    "CONTENT": "https://www.deu.ac.kr?mode=view&articleNo=53858&article.offset=0&articleLimit=10",
    "INFO_SQUARE_ID": 217
  },
  {
    "DATE": "",
    "NUMBER": "582",
    "CATEGORY": "교육모집",
    "WRITER": "국제언어교육원",
    "TITLE": "[국제언어교육원] 2025학년도 6월 모의토익 접수안내",
    "ID": 26,
    "CONTENT": "https://www.deu.ac.kr?mode=view&articleNo=71410&article.offset=0&articleLimit=10",
    "INFO_SQUARE_ID": 218
  },
  {
    "DATE": "",
    "NUMBER": "581",
    "CATEGORY": "교육모집",
    "WRITER": "국제언어교육원",
    "TITLE": "[국제언어교육원]2025학년도 하계 외국어특강 모집",
    "ID": 27,
    "CONTENT": "https://www.deu.ac.kr?mode=view&articleNo=71409&article.offset=0&articleLimit=10",
    "INFO_SQUARE_ID": 219
  },
  {
    "DATE": "",
    "NUMBER": "580",
    "CATEGORY": "교육모집",
    "WRITER": "교수학습개발센터",
    "TITLE": "[교수학습개발센터] 2025-1학기 DEU 학습심리검사 안내",
    "ID": 28,
    "CONTENT": "https://www.deu.ac.kr?mode=view&articleNo=71301&article.offset=0&articleLimit=10",
    "INFO_SQUARE_ID": 220
  },
  {
    "DATE": "",
    "NUMBER": "579",
    "CATEGORY": "교육모집",
    "WRITER": "창업교육센터",
    "TITLE": "[RISE] 2025년 「부산 U창업패키지」 모집 공고",
    "ID": 29,
    "CONTENT": "https://www.deu.ac.kr?mode=view&articleNo=71286&article.offset=0&articleLimit=10",
    "INFO_SQUARE_ID": 221
  },
  {
    "DATE": "",
    "NUMBER": "578",
    "CATEGORY": "교육모집",
    "WRITER": "창업교육센터",
    "TITLE": "금정구 청년창조발전소 꿈터플러스 「Dream-Camp 3기」모집",
    "ID": 30,
    "CONTENT": "https://www.deu.ac.kr?mode=view&articleNo=71281&article.offset=0&articleLimit=10",
    "INFO_SQUARE_ID": 222
  },
  {
    "DATE": "",
    "NUMBER": "577",
    "CATEGORY": "교육모집",
    "WRITER": "창업교육센터",
    "TITLE": "[RISE] 제8회 기상·기후테크 창업 아이디어 공모전 모집",
    "ID": 31,
    "CONTENT": "https://www.deu.ac.kr?mode=view&articleNo=71278&article.offset=0&articleLimit=10",
    "INFO_SQUARE_ID": 223
  },
  {
    "DATE": "",
    "NUMBER": "576",
    "CATEGORY": "교육모집",
    "WRITER": "RISE사업단",
    "TITLE": "[RISE] 지역 문제 해결 아이디어 공모전 모집",
    "ID": 32,
    "CONTENT": "https://www.deu.ac.kr?mode=view&articleNo=71169&article.offset=0&articleLimit=10",
    "INFO_SQUARE_ID": 224
  },
  {
    "DATE": "",
    "NUMBER": "575",
    "CATEGORY": "교육모집",
    "WRITER": "기술이전센터",
    "TITLE": "[RISE]2025년도 글로벌 기술 마케팅 프로그램 지원 공고",
    "ID": 33,
    "CONTENT": "https://www.deu.ac.kr?mode=view&articleNo=71106&article.offset=0&articleLimit=10",
    "INFO_SQUARE_ID": 225
  },
  {
    "DATE": "",
    "NUMBER": "574",
    "CATEGORY": "교육모집",
    "WRITER": "국제교류팀",
    "TITLE": "2025학년도 하계 글로벌리더십 프로그램 참가자 모집",
    "ID": 34,
    "CONTENT": "https://www.deu.ac.kr?mode=view&articleNo=71072&article.offset=0&articleLimit=10",
    "INFO_SQUARE_ID": 226
  },
  {
    "DATE": "",
    "NUMBER": "573",
    "CATEGORY": "교육모집",
    "WRITER": "국제언어교육원",
    "TITLE": "[국제언어교육원]2025학년도 BEST+ 장학 프로그램 1차 모집 안내",
    "ID": 35,
    "CONTENT": "https://www.deu.ac.kr?mode=view&articleNo=71008&article.offset=0&articleLimit=10",
    "INFO_SQUARE_ID": 227
  },
  {
    "DATE": "",
    "NUMBER": "582",
    "CATEGORY": "교육모집",
    "WRITER": "국제언어교육원",
    "TITLE": "[국제언어교육원] 2025학년도 6월 모의토익 접수안내",
    "ID": 36,
    "CONTENT": "https://www.deu.ac.kr?mode=view&articleNo=71410&article.offset=0&articleLimit=10",
    "INFO_SQUARE_ID": 228
  },
  {
    "DATE": "",
    "NUMBER": "581",
    "CATEGORY": "교육모집",
    "WRITER": "국제언어교육원",
    "TITLE": "[국제언어교육원]2025학년도 하계 외국어특강 모집",
    "ID": 37,
    "CONTENT": "https://www.deu.ac.kr?mode=view&articleNo=71409&article.offset=0&articleLimit=10",
    "INFO_SQUARE_ID": 229
  },
  {
    "DATE": "",
    "NUMBER": "580",
    "CATEGORY": "교육모집",
    "WRITER": "교수학습개발센터",
    "TITLE": "[교수학습개발센터] 2025-1학기 DEU 학습심리검사 안내",
    "ID": 38,
    "CONTENT": "https://www.deu.ac.kr?mode=view&articleNo=71301&article.offset=0&articleLimit=10",
    "INFO_SQUARE_ID": 230
  },
  {
    "DATE": "",
    "NUMBER": "579",
    "CATEGORY": "교육모집",
    "WRITER": "창업교육센터",
    "TITLE": "[RISE] 2025년 「부산 U창업패키지」 모집 공고",
    "ID": 39,
    "CONTENT": "https://www.deu.ac.kr?mode=view&articleNo=71286&article.offset=0&articleLimit=10",
    "INFO_SQUARE_ID": 231
  },
  {
    "DATE": "",
    "NUMBER": "578",
    "CATEGORY": "교육모집",
    "WRITER": "창업교육센터",
    "TITLE": "금정구 청년창조발전소 꿈터플러스 「Dream-Camp 3기」모집",
    "ID": 40,
    "CONTENT": "https://www.deu.ac.kr?mode=view&articleNo=71281&article.offset=0&articleLimit=10",
    "INFO_SQUARE_ID": 232
  },
  {
    "DATE": "",
    "NUMBER": "577",
    "CATEGORY": "교육모집",
    "WRITER": "창업교육센터",
    "TITLE": "[RISE] 제8회 기상·기후테크 창업 아이디어 공모전 모집",
    "ID": 41,
    "CONTENT": "https://www.deu.ac.kr?mode=view&articleNo=71278&article.offset=0&articleLimit=10",
    "INFO_SQUARE_ID": 233
  },
  {
    "DATE": "",
    "NUMBER": "576",
    "CATEGORY": "교육모집",
    "WRITER": "RISE사업단",
    "TITLE": "[RISE] 지역 문제 해결 아이디어 공모전 모집",
    "ID": 42,
    "CONTENT": "https://www.deu.ac.kr?mode=view&articleNo=71169&article.offset=0&articleLimit=10",
    "INFO_SQUARE_ID": 234
  },
  {
    "DATE": "",
    "NUMBER": "575",
    "CATEGORY": "교육모집",
    "WRITER": "기술이전센터",
    "TITLE": "[RISE]2025년도 글로벌 기술 마케팅 프로그램 지원 공고",
    "ID": 43,
    "CONTENT": "https://www.deu.ac.kr?mode=view&articleNo=71106&article.offset=0&articleLimit=10",
    "INFO_SQUARE_ID": 235
  },
  {
    "DATE": "",
    "NUMBER": "574",
    "CATEGORY": "교육모집",
    "WRITER": "국제교류팀",
    "TITLE": "2025학년도 하계 글로벌리더십 프로그램 참가자 모집",
    "ID": 44,
    "CONTENT": "https://www.deu.ac.kr?mode=view&articleNo=71072&article.offset=0&articleLimit=10",
    "INFO_SQUARE_ID": 236
  },
  {
    "DATE": "",
    "NUMBER": "573",
    "CATEGORY": "교육모집",
    "WRITER": "국제언어교육원",
    "TITLE": "[국제언어교육원]2025학년도 BEST+ 장학 프로그램 1차 모집 안내",
    "ID": 45,
    "CONTENT": "https://www.deu.ac.kr?mode=view&articleNo=71008&article.offset=0&articleLimit=10",
    "INFO_SQUARE_ID": 237
  },
  {
    "DATE": "",
    "NUMBER": "582",
    "CATEGORY": "교육모집",
    "WRITER": "국제언어교육원",
    "TITLE": "[국제언어교육원] 2025학년도 6월 모의토익 접수안내",
    "ID": 46,
    "CONTENT": "https://www.deu.ac.kr?mode=view&articleNo=71410&article.offset=0&articleLimit=10",
    "INFO_SQUARE_ID": 238
  },
  {
    "DATE": "",
    "NUMBER": "581",
    "CATEGORY": "교육모집",
    "WRITER": "국제언어교육원",
    "TITLE": "[국제언어교육원]2025학년도 하계 외국어특강 모집",
    "ID": 47,
    "CONTENT": "https://www.deu.ac.kr?mode=view&articleNo=71409&article.offset=0&articleLimit=10",
    "INFO_SQUARE_ID": 239
  },
  {
    "DATE": "",
    "NUMBER": "580",
    "CATEGORY": "교육모집",
    "WRITER": "교수학습개발센터",
    "TITLE": "[교수학습개발센터] 2025-1학기 DEU 학습심리검사 안내",
    "ID": 48,
    "CONTENT": "https://www.deu.ac.kr?mode=view&articleNo=71301&article.offset=0&articleLimit=10",
    "INFO_SQUARE_ID": 240
  },
  {
    "DATE": "",
    "NUMBER": "579",
    "CATEGORY": "교육모집",
    "WRITER": "창업교육센터",
    "TITLE": "[RISE] 2025년 「부산 U창업패키지」 모집 공고",
    "ID": 49,
    "CONTENT": "https://www.deu.ac.kr?mode=view&articleNo=71286&article.offset=0&articleLimit=10",
    "INFO_SQUARE_ID": 241
  },
  {
    "DATE": "",
    "NUMBER": "578",
    "CATEGORY": "교육모집",
    "WRITER": "창업교육센터",
    "TITLE": "금정구 청년창조발전소 꿈터플러스 「Dream-Camp 3기」모집",
    "ID": 50,
    "CONTENT": "https://www.deu.ac.kr?mode=view&articleNo=71281&article.offset=0&articleLimit=10",
    "INFO_SQUARE_ID": 242
  },
  {
    "DATE": "",
    "NUMBER": "577",
    "CATEGORY": "교육모집",
    "WRITER": "창업교육센터",
    "TITLE": "[RISE] 제8회 기상·기후테크 창업 아이디어 공모전 모집",
    "ID": 51,
    "CONTENT": "https://www.deu.ac.kr?mode=view&articleNo=71278&article.offset=0&articleLimit=10",
    "INFO_SQUARE_ID": 243
  },
  {
    "DATE": "",
    "NUMBER": "576",
    "CATEGORY": "교육모집",
    "WRITER": "RISE사업단",
    "TITLE": "[RISE] 지역 문제 해결 아이디어 공모전 모집",
    "ID": 52,
    "CONTENT": "https://www.deu.ac.kr?mode=view&articleNo=71169&article.offset=0&articleLimit=10",
    "INFO_SQUARE_ID": 244
  },
  {
    "DATE": "",
    "NUMBER": "575",
    "CATEGORY": "교육모집",
    "WRITER": "기술이전센터",
    "TITLE": "[RISE]2025년도 글로벌 기술 마케팅 프로그램 지원 공고",
    "ID": 53,
    "CONTENT": "https://www.deu.ac.kr?mode=view&articleNo=71106&article.offset=0&articleLimit=10",
    "INFO_SQUARE_ID": 245
  },
  {
    "DATE": "",
    "NUMBER": "574",
    "CATEGORY": "교육모집",
    "WRITER": "국제교류팀",
    "TITLE": "2025학년도 하계 글로벌리더십 프로그램 참가자 모집",
    "ID": 54,
    "CONTENT": "https://www.deu.ac.kr?mode=view&articleNo=71072&article.offset=0&articleLimit=10",
    "INFO_SQUARE_ID": 246
  },
  {
    "DATE": "",
    "NUMBER": "573",
    "CATEGORY": "교육모집",
    "WRITER": "국제언어교육원",
    "TITLE": "[국제언어교육원]2025학년도 BEST+ 장학 프로그램 1차 모집 안내",
    "ID": 55,
    "CONTENT": "https://www.deu.ac.kr?mode=view&articleNo=71008&article.offset=0&articleLimit=10",
    "INFO_SQUARE_ID": 247
  },
  {
    "DATE": "",
    "NUMBER": "582",
    "CATEGORY": "교육모집",
    "WRITER": "국제언어교육원",
    "TITLE": "[국제언어교육원] 2025학년도 6월 모의토익 접수안내",
    "ID": 56,
    "CONTENT": "https://www.deu.ac.kr?mode=view&articleNo=71410&article.offset=0&articleLimit=10",
    "INFO_SQUARE_ID": 248
  },
  {
    "DATE": "",
    "NUMBER": "581",
    "CATEGORY": "교육모집",
    "WRITER": "국제언어교육원",
    "TITLE": "[국제언어교육원]2025학년도 하계 외국어특강 모집",
    "ID": 57,
    "CONTENT": "https://www.deu.ac.kr?mode=view&articleNo=71409&article.offset=0&articleLimit=10",
    "INFO_SQUARE_ID": 249
  },
  {
    "DATE": "",
    "NUMBER": "580",
    "CATEGORY": "교육모집",
    "WRITER": "교수학습개발센터",
    "TITLE": "[교수학습개발센터] 2025-1학기 DEU 학습심리검사 안내",
    "ID": 58,
    "CONTENT": "https://www.deu.ac.kr?mode=view&articleNo=71301&article.offset=0&articleLimit=10",
    "INFO_SQUARE_ID": 250
  },
  {
    "DATE": "",
    "NUMBER": "579",
    "CATEGORY": "교육모집",
    "WRITER": "창업교육센터",
    "TITLE": "[RISE] 2025년 「부산 U창업패키지」 모집 공고",
    "ID": 59,
    "CONTENT": "https://www.deu.ac.kr?mode=view&articleNo=71286&article.offset=0&articleLimit=10",
    "INFO_SQUARE_ID": 251
  },
  {
    "DATE": "",
    "NUMBER": "578",
    "CATEGORY": "교육모집",
    "WRITER": "창업교육센터",
    "TITLE": "금정구 청년창조발전소 꿈터플러스 「Dream-Camp 3기」모집",
    "ID": 60,
    "CONTENT": "https://www.deu.ac.kr?mode=view&articleNo=71281&article.offset=0&articleLimit=10",
    "INFO_SQUARE_ID": 252
  },
  {
    "DATE": "",
    "NUMBER": "577",
    "CATEGORY": "교육모집",
    "WRITER": "창업교육센터",
    "TITLE": "[RISE] 제8회 기상·기후테크 창업 아이디어 공모전 모집",
    "ID": 61,
    "CONTENT": "https://www.deu.ac.kr?mode=view&articleNo=71278&article.offset=0&articleLimit=10",
    "INFO_SQUARE_ID": 253
  },
  {
    "DATE": "",
    "NUMBER": "576",
    "CATEGORY": "교육모집",
    "WRITER": "RISE사업단",
    "TITLE": "[RISE] 지역 문제 해결 아이디어 공모전 모집",
    "ID": 62,
    "CONTENT": "https://www.deu.ac.kr?mode=view&articleNo=71169&article.offset=0&articleLimit=10",
    "INFO_SQUARE_ID": 254
  },
  {
    "DATE": "",
    "NUMBER": "575",
    "CATEGORY": "교육모집",
    "WRITER": "기술이전센터",
    "TITLE": "[RISE]2025년도 글로벌 기술 마케팅 프로그램 지원 공고",
    "ID": 63,
    "CONTENT": "https://www.deu.ac.kr?mode=view&articleNo=71106&article.offset=0&articleLimit=10",
    "INFO_SQUARE_ID": 255
  },
  {
    "DATE": "",
    "NUMBER": "574",
    "CATEGORY": "교육모집",
    "WRITER": "국제교류팀",
    "TITLE": "2025학년도 하계 글로벌리더십 프로그램 참가자 모집",
    "ID": 64,
    "CONTENT": "https://www.deu.ac.kr?mode=view&articleNo=71072&article.offset=0&articleLimit=10",
    "INFO_SQUARE_ID": 256
  },
  {
    "DATE": "",
    "NUMBER": "573",
    "CATEGORY": "교육모집",
    "WRITER": "국제언어교육원",
    "TITLE": "[국제언어교육원]2025학년도 BEST+ 장학 프로그램 1차 모집 안내",
    "ID": 65,
    "CONTENT": "https://www.deu.ac.kr?mode=view&articleNo=71008&article.offset=0&articleLimit=10",
    "INFO_SQUARE_ID": 257
  },
  {
    "DATE": "",
    "NUMBER": "582",
    "CATEGORY": "교육모집",
    "WRITER": "국제언어교육원",
    "TITLE": "[국제언어교육원] 2025학년도 6월 모의토익 접수안내",
    "ID": 66,
    "CONTENT": "https://www.deu.ac.kr?mode=view&articleNo=71410&article.offset=0&articleLimit=10",
    "INFO_SQUARE_ID": 258
  },
  {
    "DATE": "",
    "NUMBER": "581",
    "CATEGORY": "교육모집",
    "WRITER": "국제언어교육원",
    "TITLE": "[국제언어교육원]2025학년도 하계 외국어특강 모집",
    "ID": 67,
    "CONTENT": "https://www.deu.ac.kr?mode=view&articleNo=71409&article.offset=0&articleLimit=10",
    "INFO_SQUARE_ID": 259
  },
  {
    "DATE": "",
    "NUMBER": "580",
    "CATEGORY": "교육모집",
    "WRITER": "교수학습개발센터",
    "TITLE": "[교수학습개발센터] 2025-1학기 DEU 학습심리검사 안내",
    "ID": 68,
    "CONTENT": "https://www.deu.ac.kr?mode=view&articleNo=71301&article.offset=0&articleLimit=10",
    "INFO_SQUARE_ID": 260
  },
  {
    "DATE": "",
    "NUMBER": "579",
    "CATEGORY": "교육모집",
    "WRITER": "창업교육센터",
    "TITLE": "[RISE] 2025년 「부산 U창업패키지」 모집 공고",
    "ID": 69,
    "CONTENT": "https://www.deu.ac.kr?mode=view&articleNo=71286&article.offset=0&articleLimit=10",
    "INFO_SQUARE_ID": 261
  },
  {
    "DATE": "",
    "NUMBER": "578",
    "CATEGORY": "교육모집",
    "WRITER": "창업교육센터",
    "TITLE": "금정구 청년창조발전소 꿈터플러스 「Dream-Camp 3기」모집",
    "ID": 70,
    "CONTENT": "https://www.deu.ac.kr?mode=view&articleNo=71281&article.offset=0&articleLimit=10",
    "INFO_SQUARE_ID": 262
  },
  {
    "DATE": "",
    "NUMBER": "577",
    "CATEGORY": "교육모집",
    "WRITER": "창업교육센터",
    "TITLE": "[RISE] 제8회 기상·기후테크 창업 아이디어 공모전 모집",
    "ID": 71,
    "CONTENT": "https://www.deu.ac.kr?mode=view&articleNo=71278&article.offset=0&articleLimit=10",
    "INFO_SQUARE_ID": 263
  },
  {
    "DATE": "",
    "NUMBER": "576",
    "CATEGORY": "교육모집",
    "WRITER": "RISE사업단",
    "TITLE": "[RISE] 지역 문제 해결 아이디어 공모전 모집",
    "ID": 72,
    "CONTENT": "https://www.deu.ac.kr?mode=view&articleNo=71169&article.offset=0&articleLimit=10",
    "INFO_SQUARE_ID": 264
  },
  {
    "DATE": "",
    "NUMBER": "575",
    "CATEGORY": "교육모집",
    "WRITER": "기술이전센터",
    "TITLE": "[RISE]2025년도 글로벌 기술 마케팅 프로그램 지원 공고",
    "ID": 73,
    "CONTENT": "https://www.deu.ac.kr?mode=view&articleNo=71106&article.offset=0&articleLimit=10",
    "INFO_SQUARE_ID": 265
  },
  {
    "DATE": "",
    "NUMBER": "574",
    "CATEGORY": "교육모집",
    "WRITER": "국제교류팀",
    "TITLE": "2025학년도 하계 글로벌리더십 프로그램 참가자 모집",
    "ID": 74,
    "CONTENT": "https://www.deu.ac.kr?mode=view&articleNo=71072&article.offset=0&articleLimit=10",
    "INFO_SQUARE_ID": 266
  },
  {
    "DATE": "",
    "NUMBER": "573",
    "CATEGORY": "교육모집",
    "WRITER": "국제언어교육원",
    "TITLE": "[국제언어교육원]2025학년도 BEST+ 장학 프로그램 1차 모집 안내",
    "ID": 75,
    "CONTENT": "https://www.deu.ac.kr?mode=view&articleNo=71008&article.offset=0&articleLimit=10",
    "INFO_SQUARE_ID": 267
  },
  {
    "DATE": "",
    "NUMBER": "1385",
    "CATEGORY": "장학",
    "WRITER": "장학지원팀",
    "TITLE": "2025년 상반기 강화군 대학생 등록금 지원사업 안내",
    "ID": 76,
    "CONTENT": "https://www.deu.ac.kr?mode=view&articleNo=70904&article.offset=0&articleLimit=10",
    "INFO_SQUARE_ID": 268
  },
  {
    "DATE": "",
    "NUMBER": "1384",
    "CATEGORY": "장학",
    "WRITER": "장학지원팀",
    "TITLE": "2025-1학기 국가근로 하계방학 중 집중근로 희망근로지 신청안내(이해관계자 회피 의무 준수 요망!)",
    "ID": 77,
    "CONTENT": "https://www.deu.ac.kr?mode=view&articleNo=70681&article.offset=0&articleLimit=10",
    "INFO_SQUARE_ID": 269
  },
  {
    "DATE": "",
    "NUMBER": "1383",
    "CATEGORY": "장학",
    "WRITER": "장학지원팀",
    "TITLE": "북한이탈주민장학금 신청 안내",
    "ID": 78,
    "CONTENT": "https://www.deu.ac.kr?mode=view&articleNo=69505&article.offset=0&articleLimit=10",
    "INFO_SQUARE_ID": 270
  },
  {
    "DATE": "",
    "NUMBER": "1382",
    "CATEGORY": "장학",
    "WRITER": "장학지원팀",
    "TITLE": "2025년 화성시인재육성재단 「꿈드림 장학금」 안내",
    "ID": 79,
    "CONTENT": "https://www.deu.ac.kr?mode=view&articleNo=69289&article.offset=0&articleLimit=10",
    "INFO_SQUARE_ID": 271
  },
  {
    "DATE": "",
    "NUMBER": "1381",
    "CATEGORY": "장학",
    "WRITER": "장학지원팀",
    "TITLE": "2025년도 (재)보건장학회 연구지원 장학생 선발 안내",
    "ID": 80,
    "CONTENT": "https://www.deu.ac.kr?mode=view&articleNo=68762&article.offset=0&articleLimit=10",
    "INFO_SQUARE_ID": 272
  },
  {
    "DATE": "",
    "NUMBER": "1380",
    "CATEGORY": "장학",
    "WRITER": "장학지원팀",
    "TITLE": "2025 강원랜드 멘토링 장학생 모집 안내 - 전국 폐광지역 소재 고교 졸업 재학생 해당",
    "ID": 81,
    "CONTENT": "https://www.deu.ac.kr?mode=view&articleNo=68761&article.offset=0&articleLimit=10",
    "INFO_SQUARE_ID": 273
  },
  {
    "DATE": "",
    "NUMBER": "1379",
    "CATEGORY": "장학",
    "WRITER": "장학지원팀",
    "TITLE": "2025-1학기 국가근로장학금 3차 학생신청 안내(1~2차 기신청자는 해당없음)",
    "ID": 82,
    "CONTENT": "https://www.deu.ac.kr?mode=view&articleNo=68669&article.offset=0&articleLimit=10",
    "INFO_SQUARE_ID": 274
  },
  {
    "DATE": "",
    "NUMBER": "1378",
    "CATEGORY": "장학",
    "WRITER": "장학지원팀",
    "TITLE": "2025-1학기 중소기업 취업연계 장학금(희망사다리Ⅰ유형) 신규장학생 추천 명단 안내",
    "ID": 83,
    "CONTENT": "https://www.deu.ac.kr?mode=view&articleNo=68651&article.offset=0&articleLimit=10",
    "INFO_SQUARE_ID": 275
  },
  {
    "DATE": "",
    "NUMBER": "1377",
    "CATEGORY": "장학",
    "WRITER": "장학지원팀",
    "TITLE": "2025년 제주특별자치도 학자금 대출 신용회복 지원사업 안내",
    "ID": 84,
    "CONTENT": "https://www.deu.ac.kr?mode=view&articleNo=68423&article.offset=0&articleLimit=10",
    "INFO_SQUARE_ID": 276
  },
  {
    "DATE": "",
    "NUMBER": "1376",
    "CATEGORY": "장학",
    "WRITER": "장학지원팀",
    "TITLE": "2025년 1학기 안산시 대학생 본인부담 등록금 반값지원 안내",
    "ID": 85,
    "CONTENT": "https://www.deu.ac.kr?mode=view&articleNo=68361&article.offset=0&articleLimit=10",
    "INFO_SQUARE_ID": 277
  },
  {
    "DATE": "",
    "NUMBER": "1385",
    "CATEGORY": "장학",
    "WRITER": "장학지원팀",
    "TITLE": "2025년 상반기 강화군 대학생 등록금 지원사업 안내",
    "ID": 86,
    "CONTENT": "https://www.deu.ac.kr?mode=view&articleNo=70904&article.offset=0&articleLimit=10",
    "INFO_SQUARE_ID": 278
  },
  {
    "DATE": "",
    "NUMBER": "1384",
    "CATEGORY": "장학",
    "WRITER": "장학지원팀",
    "TITLE": "2025-1학기 국가근로 하계방학 중 집중근로 희망근로지 신청안내(이해관계자 회피 의무 준수 요망!)",
    "ID": 87,
    "CONTENT": "https://www.deu.ac.kr?mode=view&articleNo=70681&article.offset=0&articleLimit=10",
    "INFO_SQUARE_ID": 279
  },
  {
    "DATE": "",
    "NUMBER": "1383",
    "CATEGORY": "장학",
    "WRITER": "장학지원팀",
    "TITLE": "북한이탈주민장학금 신청 안내",
    "ID": 88,
    "CONTENT": "https://www.deu.ac.kr?mode=view&articleNo=69505&article.offset=0&articleLimit=10",
    "INFO_SQUARE_ID": 280
  },
  {
    "DATE": "",
    "NUMBER": "1382",
    "CATEGORY": "장학",
    "WRITER": "장학지원팀",
    "TITLE": "2025년 화성시인재육성재단 「꿈드림 장학금」 안내",
    "ID": 89,
    "CONTENT": "https://www.deu.ac.kr?mode=view&articleNo=69289&article.offset=0&articleLimit=10",
    "INFO_SQUARE_ID": 281
  },
  {
    "DATE": "",
    "NUMBER": "1381",
    "CATEGORY": "장학",
    "WRITER": "장학지원팀",
    "TITLE": "2025년도 (재)보건장학회 연구지원 장학생 선발 안내",
    "ID": 90,
    "CONTENT": "https://www.deu.ac.kr?mode=view&articleNo=68762&article.offset=0&articleLimit=10",
    "INFO_SQUARE_ID": 282
  },
  {
    "DATE": "",
    "NUMBER": "1380",
    "CATEGORY": "장학",
    "WRITER": "장학지원팀",
    "TITLE": "2025 강원랜드 멘토링 장학생 모집 안내 - 전국 폐광지역 소재 고교 졸업 재학생 해당",
    "ID": 91,
    "CONTENT": "https://www.deu.ac.kr?mode=view&articleNo=68761&article.offset=0&articleLimit=10",
    "INFO_SQUARE_ID": 283
  },
  {
    "DATE": "",
    "NUMBER": "1379",
    "CATEGORY": "장학",
    "WRITER": "장학지원팀",
    "TITLE": "2025-1학기 국가근로장학금 3차 학생신청 안내(1~2차 기신청자는 해당없음)",
    "ID": 92,
    "CONTENT": "https://www.deu.ac.kr?mode=view&articleNo=68669&article.offset=0&articleLimit=10",
    "INFO_SQUARE_ID": 284
  },
  {
    "DATE": "",
    "NUMBER": "1378",
    "CATEGORY": "장학",
    "WRITER": "장학지원팀",
    "TITLE": "2025-1학기 중소기업 취업연계 장학금(희망사다리Ⅰ유형) 신규장학생 추천 명단 안내",
    "ID": 93,
    "CONTENT": "https://www.deu.ac.kr?mode=view&articleNo=68651&article.offset=0&articleLimit=10",
    "INFO_SQUARE_ID": 285
  },
  {
    "DATE": "",
    "NUMBER": "1377",
    "CATEGORY": "장학",
    "WRITER": "장학지원팀",
    "TITLE": "2025년 제주특별자치도 학자금 대출 신용회복 지원사업 안내",
    "ID": 94,
    "CONTENT": "https://www.deu.ac.kr?mode=view&articleNo=68423&article.offset=0&articleLimit=10",
    "INFO_SQUARE_ID": 286
  },
  {
    "DATE": "",
    "NUMBER": "1376",
    "CATEGORY": "장학",
    "WRITER": "장학지원팀",
    "TITLE": "2025년 1학기 안산시 대학생 본인부담 등록금 반값지원 안내",
    "ID": 95,
    "CONTENT": "https://www.deu.ac.kr?mode=view&articleNo=68361&article.offset=0&articleLimit=10",
    "INFO_SQUARE_ID": 287
  },
  {
    "DATE": "",
    "NUMBER": "1385",
    "CATEGORY": "장학",
    "WRITER": "장학지원팀",
    "TITLE": "2025년 상반기 강화군 대학생 등록금 지원사업 안내",
    "ID": 96,
    "CONTENT": "https://www.deu.ac.kr?mode=view&articleNo=70904&article.offset=0&articleLimit=10",
    "INFO_SQUARE_ID": 288
  },
  {
    "DATE": "",
    "NUMBER": "1384",
    "CATEGORY": "장학",
    "WRITER": "장학지원팀",
    "TITLE": "2025-1학기 국가근로 하계방학 중 집중근로 희망근로지 신청안내(이해관계자 회피 의무 준수 요망!)",
    "ID": 97,
    "CONTENT": "https://www.deu.ac.kr?mode=view&articleNo=70681&article.offset=0&articleLimit=10",
    "INFO_SQUARE_ID": 289
  },
  {
    "DATE": "",
    "NUMBER": "1383",
    "CATEGORY": "장학",
    "WRITER": "장학지원팀",
    "TITLE": "북한이탈주민장학금 신청 안내",
    "ID": 98,
    "CONTENT": "https://www.deu.ac.kr?mode=view&articleNo=69505&article.offset=0&articleLimit=10",
    "INFO_SQUARE_ID": 290
  },
  {
    "DATE": "",
    "NUMBER": "1382",
    "CATEGORY": "장학",
    "WRITER": "장학지원팀",
    "TITLE": "2025년 화성시인재육성재단 「꿈드림 장학금」 안내",
    "ID": 99,
    "CONTENT": "https://www.deu.ac.kr?mode=view&articleNo=69289&article.offset=0&articleLimit=10",
    "INFO_SQUARE_ID": 291
  },
  {
    "DATE": "",
    "NUMBER": "1381",
    "CATEGORY": "장학",
    "WRITER": "장학지원팀",
    "TITLE": "2025년도 (재)보건장학회 연구지원 장학생 선발 안내",
    "ID": 100,
    "CONTENT": "https://www.deu.ac.kr?mode=view&articleNo=68762&article.offset=0&articleLimit=10",
    "INFO_SQUARE_ID": 292
  },
  {
    "DATE": "",
    "NUMBER": "1380",
    "CATEGORY": "장학",
    "WRITER": "장학지원팀",
    "TITLE": "2025 강원랜드 멘토링 장학생 모집 안내 - 전국 폐광지역 소재 고교 졸업 재학생 해당",
    "ID": 101,
    "CONTENT": "https://www.deu.ac.kr?mode=view&articleNo=68761&article.offset=0&articleLimit=10",
    "INFO_SQUARE_ID": 293
  },
  {
    "DATE": "",
    "NUMBER": "1379",
    "CATEGORY": "장학",
    "WRITER": "장학지원팀",
    "TITLE": "2025-1학기 국가근로장학금 3차 학생신청 안내(1~2차 기신청자는 해당없음)",
    "ID": 102,
    "CONTENT": "https://www.deu.ac.kr?mode=view&articleNo=68669&article.offset=0&articleLimit=10",
    "INFO_SQUARE_ID": 294
  },
  {
    "DATE": "",
    "NUMBER": "1378",
    "CATEGORY": "장학",
    "WRITER": "장학지원팀",
    "TITLE": "2025-1학기 중소기업 취업연계 장학금(희망사다리Ⅰ유형) 신규장학생 추천 명단 안내",
    "ID": 103,
    "CONTENT": "https://www.deu.ac.kr?mode=view&articleNo=68651&article.offset=0&articleLimit=10",
    "INFO_SQUARE_ID": 295
  },
  {
    "DATE": "",
    "NUMBER": "1377",
    "CATEGORY": "장학",
    "WRITER": "장학지원팀",
    "TITLE": "2025년 제주특별자치도 학자금 대출 신용회복 지원사업 안내",
    "ID": 104,
    "CONTENT": "https://www.deu.ac.kr?mode=view&articleNo=68423&article.offset=0&articleLimit=10",
    "INFO_SQUARE_ID": 296
  },
  {
    "DATE": "",
    "NUMBER": "1376",
    "CATEGORY": "장학",
    "WRITER": "장학지원팀",
    "TITLE": "2025년 1학기 안산시 대학생 본인부담 등록금 반값지원 안내",
    "ID": 105,
    "CONTENT": "https://www.deu.ac.kr?mode=view&articleNo=68361&article.offset=0&articleLimit=10",
    "INFO_SQUARE_ID": 297
  },
  {
    "DATE": "",
    "NUMBER": "1385",
    "CATEGORY": "장학",
    "WRITER": "장학지원팀",
    "TITLE": "2025년 상반기 강화군 대학생 등록금 지원사업 안내",
    "ID": 106,
    "CONTENT": "https://www.deu.ac.kr?mode=view&articleNo=70904&article.offset=0&articleLimit=10",
    "INFO_SQUARE_ID": 298
  },
  {
    "DATE": "",
    "NUMBER": "1384",
    "CATEGORY": "장학",
    "WRITER": "장학지원팀",
    "TITLE": "2025-1학기 국가근로 하계방학 중 집중근로 희망근로지 신청안내(이해관계자 회피 의무 준수 요망!)",
    "ID": 107,
    "CONTENT": "https://www.deu.ac.kr?mode=view&articleNo=70681&article.offset=0&articleLimit=10",
    "INFO_SQUARE_ID": 299
  },
  {
    "DATE": "",
    "NUMBER": "1383",
    "CATEGORY": "장학",
    "WRITER": "장학지원팀",
    "TITLE": "북한이탈주민장학금 신청 안내",
    "ID": 108,
    "CONTENT": "https://www.deu.ac.kr?mode=view&articleNo=69505&article.offset=0&articleLimit=10",
    "INFO_SQUARE_ID": 300
  },
  {
    "DATE": "",
    "NUMBER": "1382",
    "CATEGORY": "장학",
    "WRITER": "장학지원팀",
    "TITLE": "2025년 화성시인재육성재단 「꿈드림 장학금」 안내",
    "ID": 109,
    "CONTENT": "https://www.deu.ac.kr?mode=view&articleNo=69289&article.offset=0&articleLimit=10",
    "INFO_SQUARE_ID": 301
  },
  {
    "DATE": "",
    "NUMBER": "1381",
    "CATEGORY": "장학",
    "WRITER": "장학지원팀",
    "TITLE": "2025년도 (재)보건장학회 연구지원 장학생 선발 안내",
    "ID": 110,
    "CONTENT": "https://www.deu.ac.kr?mode=view&articleNo=68762&article.offset=0&articleLimit=10",
    "INFO_SQUARE_ID": 302
  },
  {
    "DATE": "",
    "NUMBER": "1380",
    "CATEGORY": "장학",
    "WRITER": "장학지원팀",
    "TITLE": "2025 강원랜드 멘토링 장학생 모집 안내 - 전국 폐광지역 소재 고교 졸업 재학생 해당",
    "ID": 111,
    "CONTENT": "https://www.deu.ac.kr?mode=view&articleNo=68761&article.offset=0&articleLimit=10",
    "INFO_SQUARE_ID": 303
  },
  {
    "DATE": "",
    "NUMBER": "1379",
    "CATEGORY": "장학",
    "WRITER": "장학지원팀",
    "TITLE": "2025-1학기 국가근로장학금 3차 학생신청 안내(1~2차 기신청자는 해당없음)",
    "ID": 112,
    "CONTENT": "https://www.deu.ac.kr?mode=view&articleNo=68669&article.offset=0&articleLimit=10",
    "INFO_SQUARE_ID": 304
  },
  {
    "DATE": "",
    "NUMBER": "1378",
    "CATEGORY": "장학",
    "WRITER": "장학지원팀",
    "TITLE": "2025-1학기 중소기업 취업연계 장학금(희망사다리Ⅰ유형) 신규장학생 추천 명단 안내",
    "ID": 113,
    "CONTENT": "https://www.deu.ac.kr?mode=view&articleNo=68651&article.offset=0&articleLimit=10",
    "INFO_SQUARE_ID": 305
  },
  {
    "DATE": "",
    "NUMBER": "1377",
    "CATEGORY": "장학",
    "WRITER": "장학지원팀",
    "TITLE": "2025년 제주특별자치도 학자금 대출 신용회복 지원사업 안내",
    "ID": 114,
    "CONTENT": "https://www.deu.ac.kr?mode=view&articleNo=68423&article.offset=0&articleLimit=10",
    "INFO_SQUARE_ID": 306
  },
  {
    "DATE": "",
    "NUMBER": "1376",
    "CATEGORY": "장학",
    "WRITER": "장학지원팀",
    "TITLE": "2025년 1학기 안산시 대학생 본인부담 등록금 반값지원 안내",
    "ID": 115,
    "CONTENT": "https://www.deu.ac.kr?mode=view&articleNo=68361&article.offset=0&articleLimit=10",
    "INFO_SQUARE_ID": 307
  },
  {
    "DATE": "",
    "NUMBER": "1385",
    "CATEGORY": "장학",
    "WRITER": "장학지원팀",
    "TITLE": "2025년 상반기 강화군 대학생 등록금 지원사업 안내",
    "ID": 116,
    "CONTENT": "https://www.deu.ac.kr?mode=view&articleNo=70904&article.offset=0&articleLimit=10",
    "INFO_SQUARE_ID": 308
  },
  {
    "DATE": "",
    "NUMBER": "1384",
    "CATEGORY": "장학",
    "WRITER": "장학지원팀",
    "TITLE": "2025-1학기 국가근로 하계방학 중 집중근로 희망근로지 신청안내(이해관계자 회피 의무 준수 요망!)",
    "ID": 117,
    "CONTENT": "https://www.deu.ac.kr?mode=view&articleNo=70681&article.offset=0&articleLimit=10",
    "INFO_SQUARE_ID": 309
  },
  {
    "DATE": "",
    "NUMBER": "1383",
    "CATEGORY": "장학",
    "WRITER": "장학지원팀",
    "TITLE": "북한이탈주민장학금 신청 안내",
    "ID": 118,
    "CONTENT": "https://www.deu.ac.kr?mode=view&articleNo=69505&article.offset=0&articleLimit=10",
    "INFO_SQUARE_ID": 310
  },
  {
    "DATE": "",
    "NUMBER": "1382",
    "CATEGORY": "장학",
    "WRITER": "장학지원팀",
    "TITLE": "2025년 화성시인재육성재단 「꿈드림 장학금」 안내",
    "ID": 119,
    "CONTENT": "https://www.deu.ac.kr?mode=view&articleNo=69289&article.offset=0&articleLimit=10",
    "INFO_SQUARE_ID": 311
  },
  {
    "DATE": "",
    "NUMBER": "1381",
    "CATEGORY": "장학",
    "WRITER": "장학지원팀",
    "TITLE": "2025년도 (재)보건장학회 연구지원 장학생 선발 안내",
    "ID": 120,
    "CONTENT": "https://www.deu.ac.kr?mode=view&articleNo=68762&article.offset=0&articleLimit=10",
    "INFO_SQUARE_ID": 312
  },
  {
    "DATE": "",
    "NUMBER": "1380",
    "CATEGORY": "장학",
    "WRITER": "장학지원팀",
    "TITLE": "2025 강원랜드 멘토링 장학생 모집 안내 - 전국 폐광지역 소재 고교 졸업 재학생 해당",
    "ID": 121,
    "CONTENT": "https://www.deu.ac.kr?mode=view&articleNo=68761&article.offset=0&articleLimit=10",
    "INFO_SQUARE_ID": 313
  },
  {
    "DATE": "",
    "NUMBER": "1379",
    "CATEGORY": "장학",
    "WRITER": "장학지원팀",
    "TITLE": "2025-1학기 국가근로장학금 3차 학생신청 안내(1~2차 기신청자는 해당없음)",
    "ID": 122,
    "CONTENT": "https://www.deu.ac.kr?mode=view&articleNo=68669&article.offset=0&articleLimit=10",
    "INFO_SQUARE_ID": 314
  },
  {
    "DATE": "",
    "NUMBER": "1378",
    "CATEGORY": "장학",
    "WRITER": "장학지원팀",
    "TITLE": "2025-1학기 중소기업 취업연계 장학금(희망사다리Ⅰ유형) 신규장학생 추천 명단 안내",
    "ID": 123,
    "CONTENT": "https://www.deu.ac.kr?mode=view&articleNo=68651&article.offset=0&articleLimit=10",
    "INFO_SQUARE_ID": 315
  },
  {
    "DATE": "",
    "NUMBER": "1377",
    "CATEGORY": "장학",
    "WRITER": "장학지원팀",
    "TITLE": "2025년 제주특별자치도 학자금 대출 신용회복 지원사업 안내",
    "ID": 124,
    "CONTENT": "https://www.deu.ac.kr?mode=view&articleNo=68423&article.offset=0&articleLimit=10",
    "INFO_SQUARE_ID": 316
  },
  {
    "DATE": "",
    "NUMBER": "1376",
    "CATEGORY": "장학",
    "WRITER": "장학지원팀",
    "TITLE": "2025년 1학기 안산시 대학생 본인부담 등록금 반값지원 안내",
    "ID": 125,
    "CONTENT": "https://www.deu.ac.kr?mode=view&articleNo=68361&article.offset=0&articleLimit=10",
    "INFO_SQUARE_ID": 317
  },
  {
    "DATE": "",
    "NUMBER": "1125",
    "CATEGORY": "공지사항",
    "WRITER": "관리자",
    "TITLE": "5월 30일(금) 대표홈페이지 서버 패치 안내",
    "ID": 126,
    "CONTENT": "https://www.deu.ac.kr?mode=view&articleNo=71369&article.offset=0&articleLimit=10",
    "INFO_SQUARE_ID": 318
  },
  {
    "DATE": "",
    "NUMBER": "1124",
    "CATEGORY": "공지사항",
    "WRITER": "학사지원팀",
    "TITLE": "2025학년도 2학기 재입학 안내",
    "ID": 127,
    "CONTENT": "https://www.deu.ac.kr?mode=view&articleNo=71345&article.offset=0&articleLimit=10",
    "INFO_SQUARE_ID": 319
  },
  {
    "DATE": "",
    "NUMBER": "1123",
    "CATEGORY": "공지사항",
    "WRITER": "예비군연대",
    "TITLE": "[예비군연대] 2025년 학생 예비군(공과대학 등) 훈련 안내",
    "ID": 128,
    "CONTENT": "https://www.deu.ac.kr?mode=view&articleNo=71069&article.offset=0&articleLimit=10",
    "INFO_SQUARE_ID": 320
  },
  {
    "DATE": "",
    "NUMBER": "1122",
    "CATEGORY": "공지사항",
    "WRITER": "국제교류팀",
    "TITLE": "[RISE] 외국인 유학생 International Festival 행사 안내",
    "ID": 129,
    "CONTENT": "https://www.deu.ac.kr?mode=view&articleNo=70945&article.offset=0&articleLimit=10",
    "INFO_SQUARE_ID": 321
  },
  {
    "DATE": "",
    "NUMBER": "1121",
    "CATEGORY": "공지사항",
    "WRITER": "대외협력팀",
    "TITLE": "[신규 후원의 집] \"효민디앤피\" 이용 안내",
    "ID": 130,
    "CONTENT": "https://www.deu.ac.kr?mode=view&articleNo=70755&article.offset=0&articleLimit=10",
    "INFO_SQUARE_ID": 322
  },
  {
    "DATE": "",
    "NUMBER": "1120",
    "CATEGORY": "공지사항",
    "WRITER": "경리팀",
    "TITLE": "2025학년도 1학기 등록금 분할4차 납부 안내",
    "ID": 131,
    "CONTENT": "https://www.deu.ac.kr?mode=view&articleNo=70742&article.offset=0&articleLimit=10",
    "INFO_SQUARE_ID": 323
  },
  {
    "DATE": "",
    "NUMBER": "1119",
    "CATEGORY": "공지사항",
    "WRITER": "국제교류팀",
    "TITLE": "[국제교류팀] 2025 대동제 플리마켓에서 추억이 담긴 물건 나눠 담아요!",
    "ID": 132,
    "CONTENT": "https://www.deu.ac.kr?mode=view&articleNo=70727&article.offset=0&articleLimit=10",
    "INFO_SQUARE_ID": 324
  },
  {
    "DATE": "",
    "NUMBER": "1118",
    "CATEGORY": "공지사항",
    "WRITER": "학생지원팀",
    "TITLE": "2025 대동제(축제) 외부인 공연장 입장 및 차량 제한 안내",
    "ID": 133,
    "CONTENT": "https://www.deu.ac.kr?mode=view&articleNo=70714&article.offset=0&articleLimit=10",
    "INFO_SQUARE_ID": 325
  },
  {
    "DATE": "",
    "NUMBER": "1117",
    "CATEGORY": "공지사항",
    "WRITER": "미래교육원",
    "TITLE": "[미래교육원]제3회 동의대학교 미래교육원 민화 전시회",
    "ID": 134,
    "CONTENT": "https://www.deu.ac.kr?mode=view&articleNo=70595&article.offset=0&articleLimit=10",
    "INFO_SQUARE_ID": 326
  },
  {
    "DATE": "",
    "NUMBER": "1116",
    "CATEGORY": "공지사항",
    "WRITER": "박물관",
    "TITLE": "[동의대박물관] 2025년 상반기 특별전 <나에게로 떠나는 여행> 개최",
    "ID": 135,
    "CONTENT": "https://www.deu.ac.kr?mode=view&articleNo=69406&article.offset=0&articleLimit=10",
    "INFO_SQUARE_ID": 327
  },
  {
    "DATE": "",
    "NUMBER": "1125",
    "CATEGORY": "공지사항",
    "WRITER": "관리자",
    "TITLE": "5월 30일(금) 대표홈페이지 서버 패치 안내",
    "ID": 136,
    "CONTENT": "https://www.deu.ac.kr?mode=view&articleNo=71369&article.offset=0&articleLimit=10",
    "INFO_SQUARE_ID": 328
  },
  {
    "DATE": "",
    "NUMBER": "1124",
    "CATEGORY": "공지사항",
    "WRITER": "학사지원팀",
    "TITLE": "2025학년도 2학기 재입학 안내",
    "ID": 137,
    "CONTENT": "https://www.deu.ac.kr?mode=view&articleNo=71345&article.offset=0&articleLimit=10",
    "INFO_SQUARE_ID": 329
  },
  {
    "DATE": "",
    "NUMBER": "1123",
    "CATEGORY": "공지사항",
    "WRITER": "예비군연대",
    "TITLE": "[예비군연대] 2025년 학생 예비군(공과대학 등) 훈련 안내",
    "ID": 138,
    "CONTENT": "https://www.deu.ac.kr?mode=view&articleNo=71069&article.offset=0&articleLimit=10",
    "INFO_SQUARE_ID": 330
  },
  {
    "DATE": "",
    "NUMBER": "1122",
    "CATEGORY": "공지사항",
    "WRITER": "국제교류팀",
    "TITLE": "[RISE] 외국인 유학생 International Festival 행사 안내",
    "ID": 139,
    "CONTENT": "https://www.deu.ac.kr?mode=view&articleNo=70945&article.offset=0&articleLimit=10",
    "INFO_SQUARE_ID": 331
  },
  {
    "DATE": "",
    "NUMBER": "1121",
    "CATEGORY": "공지사항",
    "WRITER": "대외협력팀",
    "TITLE": "[신규 후원의 집] \"효민디앤피\" 이용 안내",
    "ID": 140,
    "CONTENT": "https://www.deu.ac.kr?mode=view&articleNo=70755&article.offset=0&articleLimit=10",
    "INFO_SQUARE_ID": 332
  },
  {
    "DATE": "",
    "NUMBER": "1120",
    "CATEGORY": "공지사항",
    "WRITER": "경리팀",
    "TITLE": "2025학년도 1학기 등록금 분할4차 납부 안내",
    "ID": 141,
    "CONTENT": "https://www.deu.ac.kr?mode=view&articleNo=70742&article.offset=0&articleLimit=10",
    "INFO_SQUARE_ID": 333
  },
  {
    "DATE": "",
    "NUMBER": "1119",
    "CATEGORY": "공지사항",
    "WRITER": "국제교류팀",
    "TITLE": "[국제교류팀] 2025 대동제 플리마켓에서 추억이 담긴 물건 나눠 담아요!",
    "ID": 142,
    "CONTENT": "https://www.deu.ac.kr?mode=view&articleNo=70727&article.offset=0&articleLimit=10",
    "INFO_SQUARE_ID": 334
  },
  {
    "DATE": "",
    "NUMBER": "1118",
    "CATEGORY": "공지사항",
    "WRITER": "학생지원팀",
    "TITLE": "2025 대동제(축제) 외부인 공연장 입장 및 차량 제한 안내",
    "ID": 143,
    "CONTENT": "https://www.deu.ac.kr?mode=view&articleNo=70714&article.offset=0&articleLimit=10",
    "INFO_SQUARE_ID": 335
  },
  {
    "DATE": "",
    "NUMBER": "1117",
    "CATEGORY": "공지사항",
    "WRITER": "미래교육원",
    "TITLE": "[미래교육원]제3회 동의대학교 미래교육원 민화 전시회",
    "ID": 144,
    "CONTENT": "https://www.deu.ac.kr?mode=view&articleNo=70595&article.offset=0&articleLimit=10",
    "INFO_SQUARE_ID": 336
  },
  {
    "DATE": "",
    "NUMBER": "1116",
    "CATEGORY": "공지사항",
    "WRITER": "박물관",
    "TITLE": "[동의대박물관] 2025년 상반기 특별전 <나에게로 떠나는 여행> 개최",
    "ID": 145,
    "CONTENT": "https://www.deu.ac.kr?mode=view&articleNo=69406&article.offset=0&articleLimit=10",
    "INFO_SQUARE_ID": 337
  },
  {
    "DATE": "",
    "NUMBER": "1125",
    "CATEGORY": "공지사항",
    "WRITER": "관리자",
    "TITLE": "5월 30일(금) 대표홈페이지 서버 패치 안내",
    "ID": 146,
    "CONTENT": "https://www.deu.ac.kr?mode=view&articleNo=71369&article.offset=0&articleLimit=10",
    "INFO_SQUARE_ID": 338
  },
  {
    "DATE": "",
    "NUMBER": "1124",
    "CATEGORY": "공지사항",
    "WRITER": "학사지원팀",
    "TITLE": "2025학년도 2학기 재입학 안내",
    "ID": 147,
    "CONTENT": "https://www.deu.ac.kr?mode=view&articleNo=71345&article.offset=0&articleLimit=10",
    "INFO_SQUARE_ID": 339
  },
  {
    "DATE": "",
    "NUMBER": "1123",
    "CATEGORY": "공지사항",
    "WRITER": "예비군연대",
    "TITLE": "[예비군연대] 2025년 학생 예비군(공과대학 등) 훈련 안내",
    "ID": 148,
    "CONTENT": "https://www.deu.ac.kr?mode=view&articleNo=71069&article.offset=0&articleLimit=10",
    "INFO_SQUARE_ID": 340
  },
  {
    "DATE": "",
    "NUMBER": "1122",
    "CATEGORY": "공지사항",
    "WRITER": "국제교류팀",
    "TITLE": "[RISE] 외국인 유학생 International Festival 행사 안내",
    "ID": 149,
    "CONTENT": "https://www.deu.ac.kr?mode=view&articleNo=70945&article.offset=0&articleLimit=10",
    "INFO_SQUARE_ID": 341
  },
  {
    "DATE": "",
    "NUMBER": "1121",
    "CATEGORY": "공지사항",
    "WRITER": "대외협력팀",
    "TITLE": "[신규 후원의 집] \"효민디앤피\" 이용 안내",
    "ID": 150,
    "CONTENT": "https://www.deu.ac.kr?mode=view&articleNo=70755&article.offset=0&articleLimit=10",
    "INFO_SQUARE_ID": 342
  },
  {
    "DATE": "",
    "NUMBER": "1120",
    "CATEGORY": "공지사항",
    "WRITER": "경리팀",
    "TITLE": "2025학년도 1학기 등록금 분할4차 납부 안내",
    "ID": 151,
    "CONTENT": "https://www.deu.ac.kr?mode=view&articleNo=70742&article.offset=0&articleLimit=10",
    "INFO_SQUARE_ID": 343
  },
  {
    "DATE": "",
    "NUMBER": "1119",
    "CATEGORY": "공지사항",
    "WRITER": "국제교류팀",
    "TITLE": "[국제교류팀] 2025 대동제 플리마켓에서 추억이 담긴 물건 나눠 담아요!",
    "ID": 152,
    "CONTENT": "https://www.deu.ac.kr?mode=view&articleNo=70727&article.offset=0&articleLimit=10",
    "INFO_SQUARE_ID": 344
  },
  {
    "DATE": "",
    "NUMBER": "1118",
    "CATEGORY": "공지사항",
    "WRITER": "학생지원팀",
    "TITLE": "2025 대동제(축제) 외부인 공연장 입장 및 차량 제한 안내",
    "ID": 153,
    "CONTENT": "https://www.deu.ac.kr?mode=view&articleNo=70714&article.offset=0&articleLimit=10",
    "INFO_SQUARE_ID": 345
  },
  {
    "DATE": "",
    "NUMBER": "1117",
    "CATEGORY": "공지사항",
    "WRITER": "미래교육원",
    "TITLE": "[미래교육원]제3회 동의대학교 미래교육원 민화 전시회",
    "ID": 154,
    "CONTENT": "https://www.deu.ac.kr?mode=view&articleNo=70595&article.offset=0&articleLimit=10",
    "INFO_SQUARE_ID": 346
  },
  {
    "DATE": "",
    "NUMBER": "1116",
    "CATEGORY": "공지사항",
    "WRITER": "박물관",
    "TITLE": "[동의대박물관] 2025년 상반기 특별전 <나에게로 떠나는 여행> 개최",
    "ID": 155,
    "CONTENT": "https://www.deu.ac.kr?mode=view&articleNo=69406&article.offset=0&articleLimit=10",
    "INFO_SQUARE_ID": 347
  },
  {
    "DATE": "",
    "NUMBER": "1125",
    "CATEGORY": "공지사항",
    "WRITER": "관리자",
    "TITLE": "5월 30일(금) 대표홈페이지 서버 패치 안내",
    "ID": 156,
    "CONTENT": "https://www.deu.ac.kr?mode=view&articleNo=71369&article.offset=0&articleLimit=10",
    "INFO_SQUARE_ID": 348
  },
  {
    "DATE": "",
    "NUMBER": "1124",
    "CATEGORY": "공지사항",
    "WRITER": "학사지원팀",
    "TITLE": "2025학년도 2학기 재입학 안내",
    "ID": 157,
    "CONTENT": "https://www.deu.ac.kr?mode=view&articleNo=71345&article.offset=0&articleLimit=10",
    "INFO_SQUARE_ID": 349
  },
  {
    "DATE": "",
    "NUMBER": "1123",
    "CATEGORY": "공지사항",
    "WRITER": "예비군연대",
    "TITLE": "[예비군연대] 2025년 학생 예비군(공과대학 등) 훈련 안내",
    "ID": 158,
    "CONTENT": "https://www.deu.ac.kr?mode=view&articleNo=71069&article.offset=0&articleLimit=10",
    "INFO_SQUARE_ID": 350
  },
  {
    "DATE": "",
    "NUMBER": "1122",
    "CATEGORY": "공지사항",
    "WRITER": "국제교류팀",
    "TITLE": "[RISE] 외국인 유학생 International Festival 행사 안내",
    "ID": 159,
    "CONTENT": "https://www.deu.ac.kr?mode=view&articleNo=70945&article.offset=0&articleLimit=10",
    "INFO_SQUARE_ID": 351
  },
  {
    "DATE": "",
    "NUMBER": "1121",
    "CATEGORY": "공지사항",
    "WRITER": "대외협력팀",
    "TITLE": "[신규 후원의 집] \"효민디앤피\" 이용 안내",
    "ID": 160,
    "CONTENT": "https://www.deu.ac.kr?mode=view&articleNo=70755&article.offset=0&articleLimit=10",
    "INFO_SQUARE_ID": 352
  },
  {
    "DATE": "",
    "NUMBER": "1120",
    "CATEGORY": "공지사항",
    "WRITER": "경리팀",
    "TITLE": "2025학년도 1학기 등록금 분할4차 납부 안내",
    "ID": 161,
    "CONTENT": "https://www.deu.ac.kr?mode=view&articleNo=70742&article.offset=0&articleLimit=10",
    "INFO_SQUARE_ID": 353
  },
  {
    "DATE": "",
    "NUMBER": "1119",
    "CATEGORY": "공지사항",
    "WRITER": "국제교류팀",
    "TITLE": "[국제교류팀] 2025 대동제 플리마켓에서 추억이 담긴 물건 나눠 담아요!",
    "ID": 162,
    "CONTENT": "https://www.deu.ac.kr?mode=view&articleNo=70727&article.offset=0&articleLimit=10",
    "INFO_SQUARE_ID": 354
  },
  {
    "DATE": "",
    "NUMBER": "1118",
    "CATEGORY": "공지사항",
    "WRITER": "학생지원팀",
    "TITLE": "2025 대동제(축제) 외부인 공연장 입장 및 차량 제한 안내",
    "ID": 163,
    "CONTENT": "https://www.deu.ac.kr?mode=view&articleNo=70714&article.offset=0&articleLimit=10",
    "INFO_SQUARE_ID": 355
  },
  {
    "DATE": "",
    "NUMBER": "1117",
    "CATEGORY": "공지사항",
    "WRITER": "미래교육원",
    "TITLE": "[미래교육원]제3회 동의대학교 미래교육원 민화 전시회",
    "ID": 164,
    "CONTENT": "https://www.deu.ac.kr?mode=view&articleNo=70595&article.offset=0&articleLimit=10",
    "INFO_SQUARE_ID": 356
  },
  {
    "DATE": "",
    "NUMBER": "1116",
    "CATEGORY": "공지사항",
    "WRITER": "박물관",
    "TITLE": "[동의대박물관] 2025년 상반기 특별전 <나에게로 떠나는 여행> 개최",
    "ID": 165,
    "CONTENT": "https://www.deu.ac.kr?mode=view&articleNo=69406&article.offset=0&articleLimit=10",
    "INFO_SQUARE_ID": 357
  },
  {
    "DATE": "",
    "NUMBER": "1125",
    "CATEGORY": "공지사항",
    "WRITER": "관리자",
    "TITLE": "5월 30일(금) 대표홈페이지 서버 패치 안내",
    "ID": 166,
    "CONTENT": "https://www.deu.ac.kr?mode=view&articleNo=71369&article.offset=0&articleLimit=10",
    "INFO_SQUARE_ID": 358
  },
  {
    "DATE": "",
    "NUMBER": "1124",
    "CATEGORY": "공지사항",
    "WRITER": "학사지원팀",
    "TITLE": "2025학년도 2학기 재입학 안내",
    "ID": 167,
    "CONTENT": "https://www.deu.ac.kr?mode=view&articleNo=71345&article.offset=0&articleLimit=10",
    "INFO_SQUARE_ID": 359
  },
  {
    "DATE": "",
    "NUMBER": "1123",
    "CATEGORY": "공지사항",
    "WRITER": "예비군연대",
    "TITLE": "[예비군연대] 2025년 학생 예비군(공과대학 등) 훈련 안내",
    "ID": 168,
    "CONTENT": "https://www.deu.ac.kr?mode=view&articleNo=71069&article.offset=0&articleLimit=10",
    "INFO_SQUARE_ID": 360
  },
  {
    "DATE": "",
    "NUMBER": "1122",
    "CATEGORY": "공지사항",
    "WRITER": "국제교류팀",
    "TITLE": "[RISE] 외국인 유학생 International Festival 행사 안내",
    "ID": 169,
    "CONTENT": "https://www.deu.ac.kr?mode=view&articleNo=70945&article.offset=0&articleLimit=10",
    "INFO_SQUARE_ID": 361
  },
  {
    "DATE": "",
    "NUMBER": "1121",
    "CATEGORY": "공지사항",
    "WRITER": "대외협력팀",
    "TITLE": "[신규 후원의 집] \"효민디앤피\" 이용 안내",
    "ID": 170,
    "CONTENT": "https://www.deu.ac.kr?mode=view&articleNo=70755&article.offset=0&articleLimit=10",
    "INFO_SQUARE_ID": 362
  },
  {
    "DATE": "",
    "NUMBER": "1120",
    "CATEGORY": "공지사항",
    "WRITER": "경리팀",
    "TITLE": "2025학년도 1학기 등록금 분할4차 납부 안내",
    "ID": 171,
    "CONTENT": "https://www.deu.ac.kr?mode=view&articleNo=70742&article.offset=0&articleLimit=10",
    "INFO_SQUARE_ID": 363
  },
  {
    "DATE": "",
    "NUMBER": "1119",
    "CATEGORY": "공지사항",
    "WRITER": "국제교류팀",
    "TITLE": "[국제교류팀] 2025 대동제 플리마켓에서 추억이 담긴 물건 나눠 담아요!",
    "ID": 172,
    "CONTENT": "https://www.deu.ac.kr?mode=view&articleNo=70727&article.offset=0&articleLimit=10",
    "INFO_SQUARE_ID": 364
  },
  {
    "DATE": "",
    "NUMBER": "1118",
    "CATEGORY": "공지사항",
    "WRITER": "학생지원팀",
    "TITLE": "2025 대동제(축제) 외부인 공연장 입장 및 차량 제한 안내",
    "ID": 173,
    "CONTENT": "https://www.deu.ac.kr?mode=view&articleNo=70714&article.offset=0&articleLimit=10",
    "INFO_SQUARE_ID": 365
  },
  {
    "DATE": "",
    "NUMBER": "1117",
    "CATEGORY": "공지사항",
    "WRITER": "미래교육원",
    "TITLE": "[미래교육원]제3회 동의대학교 미래교육원 민화 전시회",
    "ID": 174,
    "CONTENT": "https://www.deu.ac.kr?mode=view&articleNo=70595&article.offset=0&articleLimit=10",
    "INFO_SQUARE_ID": 366
  },
  {
    "DATE": "",
    "NUMBER": "1116",
    "CATEGORY": "공지사항",
    "WRITER": "박물관",
    "TITLE": "[동의대박물관] 2025년 상반기 특별전 <나에게로 떠나는 여행> 개최",
    "ID": 175,
    "CONTENT": "https://www.deu.ac.kr?mode=view&articleNo=69406&article.offset=0&articleLimit=10",
    "INFO_SQUARE_ID": 367
  }
]